boilerplatetool.py
boilerplatetool-0.1.0.dist-info/entry_points.txt
boilerplatetool-0.1.0.dist-info/WHEEL
boilerplatetool-0.1.0.dist-info/METADATA
boilerplatetool-0.1.0.dist-info/RECORD
