Metadata-Version: 2.1
Name: boilerplatetool
Version: 0.1.0
Summary: A CLI Tool for creating boilerplate code for popular frameworks like Vue,Flutter,Django etc
License: MIT
Author: Vishnu Varthan
Requires-Python: >=3.7,<4.0
Classifier: License :: OSI Approved :: MIT License
Classifier: Programming Language :: Python :: 3
Classifier: Programming Language :: Python :: 3.7
